django_jwt_auth-0.0.2.dist-info/DESCRIPTION.rst
django_jwt_auth-0.0.2.dist-info/METADATA
django_jwt_auth-0.0.2.dist-info/metadata.json
django_jwt_auth-0.0.2.dist-info/RECORD
django_jwt_auth-0.0.2.dist-info/top_level.txt
django_jwt_auth-0.0.2.dist-info/WHEEL
jwt_auth/__init__.py
jwt_auth/compat.py
jwt_auth/exceptions.py
jwt_auth/forms.py
jwt_auth/mixins.py
jwt_auth/settings.py
jwt_auth/utils.py
jwt_auth/views.py
